TelegramBotNotifications/__init__.py
TelegramBotNotifications/core.py
TelegramBotNotifications-0.0.2.dist-info/METADATA
TelegramBotNotifications-0.0.2.dist-info/WHEEL
TelegramBotNotifications-0.0.2.dist-info/top_level.txt
TelegramBotNotifications-0.0.2.dist-info/RECORD
