Metadata-Version: 2.1
Name: TelegramBotNotifications
Version: 0.0.2
Summary: UNKNOWN
Home-page: https://github.com/giocaizzi/TelegramBotNotifications
Author: giocaizzi
Author-email: giocaizzi@gmail.com
License: UNKNOWN
Project-URL: Documentation, https://giocaizzi.github.io/TelegramBotNotifications/
Project-URL: Bug Reports, https://github.com/giocaizzi/TelegramBotNotifications/issues
Project-URL: Source, https://github.com/giocaizzi/TelegramBotNotifications
Platform: UNKNOWN
Classifier: Programming Language :: Python :: 3.7
Classifier: Programming Language :: Python :: 3.8
Classifier: Programming Language :: Python :: 3.9
Requires-Dist: python-telegram-bot
Requires-Dist: pandas
Requires-Dist: numpy
Provides-Extra: dev
